inaSpeechSegmenter/__init__.py
inaSpeechSegmenter/constants.py
inaSpeechSegmenter/features.py
inaSpeechSegmenter/segmenter.py
inaSpeechSegmenter/sidekit_mfcc.py
inaSpeechSegmenter/skimage_vaw.py
inaSpeechSegmenter/tf_mfcc.py
inaSpeechSegmenter/viterbi_utils.py
inaSpeechSegmenter/util/__init__.py
inaSpeechSegmenter/util/pyannote_viterbi.py
ina_segmenter_modified-1.0.7.dist-info/LICENSE
ina_segmenter_modified-1.0.7.dist-info/METADATA
ina_segmenter_modified-1.0.7.dist-info/WHEEL
ina_segmenter_modified-1.0.7.dist-info/top_level.txt
ina_segmenter_modified-1.0.7.dist-info/RECORD
