Metadata-Version: 2.1
Name: ina-segmenter-modified
Version: 1.0.7
Summary: Modified version of Ina Speech Segmenter
Home-page: https://github.com/youquzhiji/voice-cnn
Author: Azalea Gui
Author-email: hykilpikonna@gmail.com
License: MIT
Platform: UNKNOWN
Requires-Python: >=3.8
License-File: LICENSE
Requires-Dist: tensorflow
Requires-Dist: tensorflow-io
Requires-Dist: numpy
Requires-Dist: soundfile
Requires-Dist: numba
